Flask_Spec-0.0.0a2.dist-info/METADATA
Flask_Spec-0.0.0a2.dist-info/RECORD
Flask_Spec-0.0.0a2.dist-info/WHEEL
Flask_Spec-0.0.0a2.dist-info/top_level.txt
flask_spec/__init__.py
flask_spec/extensions.py
flask_spec/registars.py
flask_spec/utils.py
flask_spec/templates/envs.html
