Metadata-Version: 2.1
Name: Flask-Spec
Version: 0.0.0a2
Summary: A lightweight wrapper around apispec for extracting OpenApi specs from flask project.
Home-page: https://github.com/ArtemAngelchev/flask-spec
Author: Angelchev Artem
Author-email: artangelchev@gmail.com
License: MIT
Keywords: swagger,apispec,openapi,documentation,docs,api,rest
Platform: UNKNOWN
Classifier: Intended Audience :: Developers
Classifier: Programming Language :: Python :: 3.6
Classifier: Programming Language :: Python :: 3.7
Classifier: Programming Language :: Python :: 3 :: Only
Requires-Dist: Flask (>=0.10)
Requires-Dist: marshmallow (>=2.0.0)
Requires-Dist: apispec (>=0.17.0)
Requires-Dist: markdown2 (>=2.0.0)
